{
    "ADaCGH2": [
        "snapCGH",
        "tilingArray"
    ],
    "affycoretools": [
        "ReportingTools",
        "VariantAnnotation",
        "biovizBase",
        "ggbio"
    ],
    "AgiMicroRna": [
        "ReportingTools",
        "VariantAnnotation",
        "affycoretools",
        "biovizBase",
        "ggbio"
    ],
    "AHMassBank": [
        "AnnotationHubData"
    ],
    "airpart": [
        "scater"
    ],
    "alabaster": [
        "SpatialExperiment",
        "VariantAnnotation",
        "alabaster.spatial",
        "alabaster.vcf"
    ],
    "alabaster.spatial": [
        "SpatialExperiment"
    ],
    "alabaster.vcf": [
        "VariantAnnotation"
    ],
    "AllelicImbalance": [
        "Gviz",
        "VariantAnnotation",
        "biovizBase"
    ],
    "alpine": [],
    "amplican": [],
    "ANCOMBC": [
        "mia",
        "scater"
    ],
    "AnnotationHubData": [],
    "annotatr": [
        "regioneR"
    ],
    "APAlyzer": [
        "VariantAnnotation"
    ],
    "appreci8R": [
        "VariantAnnotation"
    ],
    "arrayMvout": [
        "lumi",
        "methylumi",
        "minfi"
    ],
    "ASpli": [
        "Gviz",
        "VariantAnnotation",
        "biovizBase"
    ],
    "ATACCoGAPS": [
        "TFBSTools",
        "chromVAR",
        "motifmatchr",
        "projectR",
        "rGREAT"
    ],
    "ATACseqQC": [
        "ChIPpeakAnno",
        "TFBSTools",
        "motifStack",
        "regioneR"
    ],
    "ATACseqTFEA": [
        "TFBSTools",
        "motifmatchr"
    ],
    "atSNP": [
        "TFBSTools",
        "motifStack"
    ],
    "BadRegionFinder": [
        "VariantAnnotation"
    ],
    "bandle": [
        "pRoloc"
    ],
    "BASiCS": [
        "scran"
    ],
    "BASiCStan": [
        "BASiCS",
        "scran"
    ],
    "BayesSpace": [
        "scater",
        "scran"
    ],
    "BBCAnalyzer": [
        "VariantAnnotation"
    ],
    "BEAT": [],
    "benchdamic": [
        "ANCOMBC",
        "mia",
        "scater",
        "zinbwave"
    ],
    "BGmix": [],
    "bigmelon": [
        "lumi",
        "methylumi",
        "minfi",
        "wateRmelon"
    ],
    "BindingSiteFinder": [
        "Gviz",
        "VariantAnnotation",
        "biovizBase"
    ],
    "BioTIP": [
        "scran"
    ],
    "biovizBase": [
        "VariantAnnotation"
    ],
    "biscuiteer": [
        "VariantAnnotation",
        "annotatr",
        "dmrseq",
        "regioneR"
    ],
    "BiSeq": [],
    "BOBaFIT": [
        "VariantAnnotation",
        "biovizBase",
        "ggbio"
    ],
    "borealis": [
        "DSS"
    ],
    "brainflowprobes": [
        "GenomicFiles",
        "VariantAnnotation",
        "biovizBase",
        "derfinder",
        "derfinderPlot",
        "ggbio"
    ],
    "branchpointer": [],
    "BubbleTree": [
        "VariantAnnotation",
        "biovizBase"
    ],
    "CAFE": [
        "VariantAnnotation",
        "biovizBase",
        "ggbio"
    ],
    "CAGEfightR": [
        "GenomicFiles",
        "GenomicInteractions",
        "Gviz",
        "VariantAnnotation",
        "biovizBase"
    ],
    "cageminer": [
        "VariantAnnotation",
        "biovizBase",
        "ggbio"
    ],
    "CAGEr": [
        "CAGEfightR",
        "GenomicFiles",
        "GenomicInteractions",
        "Gviz",
        "VariantAnnotation",
        "biovizBase"
    ],
    "canceR": [
        "phenoTest"
    ],
    "cardelino": [
        "VariantAnnotation"
    ],
    "CATALYST": [
        "scater"
    ],
    "cbaf": [
        "RTCGAToolbox",
        "cBioPortalData"
    ],
    "cBioPortalData": [
        "RTCGAToolbox"
    ],
    "CCPROMISE": [],
    "celda": [
        "scater",
        "scran"
    ],
    "cellHTS2": [],
    "CelliD": [
        "scater"
    ],
    "CellMixS": [
        "scater"
    ],
    "CEMiTool": [],
    "CeTF": [],
    "CexoR": [
        "genomation"
    ],
    "cfDNAPro": [],
    "ChAMP": [
        "DMRcate",
        "DSS",
        "Gviz",
        "VariantAnnotation",
        "biovizBase",
        "lumi",
        "methylumi",
        "minfi",
        "missMethyl",
        "wateRmelon"
    ],
    "ChIC": [],
    "chimeraviz": [
        "Gviz",
        "VariantAnnotation",
        "biovizBase"
    ],
    "ChIPanalyser": [],
    "ChIPComp": [],
    "ChIPexoQual": [
        "VariantAnnotation",
        "biovizBase"
    ],
    "ChIPpeakAnno": [
        "regioneR"
    ],
    "ChIPQC": [
        "DiffBind",
        "GreyListChIP"
    ],
    "ChromSCape": [
        "scater",
        "scran"
    ],
    "chromVAR": [
        "TFBSTools"
    ],
    "cicero": [
        "Gviz",
        "VariantAnnotation",
        "biovizBase"
    ],
    "circRNAprofiler": [
        "VariantAnnotation",
        "gwascat"
    ],
    "CircSeqAlignTk": [
        "Rhisat2"
    ],
    "CiteFuse": [
        "scran"
    ],
    "cleanUpdTSeq": [],
    "clipper": [],
    "clusterExperiment": [
        "zinbwave"
    ],
    "CNVfilteR": [
        "CopyNumberPlots",
        "VariantAnnotation",
        "biovizBase",
        "karyoploteR",
        "regioneR"
    ],
    "CNViz": [
        "CopyNumberPlots",
        "VariantAnnotation",
        "biovizBase",
        "karyoploteR",
        "regioneR"
    ],
    "CNVrd2": [
        "VariantAnnotation"
    ],
    "COCOA": [
        "MIRA"
    ],
    "CODEX": [],
    "comapr": [
        "Gviz",
        "VariantAnnotation",
        "biovizBase"
    ],
    "coMET": [
        "Gviz",
        "VariantAnnotation",
        "biovizBase"
    ],
    "coMethDMR": [],
    "compEpiTools": [
        "Gviz",
        "VariantAnnotation",
        "biovizBase",
        "methylPipe"
    ],
    "condiments": [
        "distinct",
        "scater",
        "slingshot"
    ],
    "consensusDE": [
        "RUVSeq"
    ],
    "contiBAIT": [
        "GenomicFiles",
        "VariantAnnotation"
    ],
    "conumee": [
        "minfi"
    ],
    "CopyNumberPlots": [
        "VariantAnnotation",
        "biovizBase",
        "karyoploteR",
        "regioneR"
    ],
    "crisprBowtie": [],
    "crisprBwa": [],
    "crisprDesign": [
        "VariantAnnotation",
        "crisprBowtie"
    ],
    "CRISPRseek": [],
    "crisprseekplus": [
        "CRISPRseek",
        "ChIPpeakAnno",
        "GUIDEseq",
        "regioneR"
    ],
    "crisprVerse": [
        "Gviz",
        "VariantAnnotation",
        "biovizBase",
        "crisprBowtie",
        "crisprDesign",
        "crisprViz"
    ],
    "crisprViz": [
        "Gviz",
        "VariantAnnotation",
        "biovizBase",
        "crisprBowtie",
        "crisprDesign"
    ],
    "CTSV": [
        "SpatialExperiment"
    ],
    "cummeRbund": [
        "Gviz",
        "VariantAnnotation",
        "biovizBase"
    ],
    "customProDB": [
        "VariantAnnotation"
    ],
    "cytofQC": [
        "CATALYST",
        "scater"
    ],
    "cytomapper": [
        "SpatialExperiment"
    ],
    "cytoviewer": [
        "SpatialExperiment",
        "cytomapper"
    ],
    "dagLogo": [
        "TFBSTools",
        "motifStack"
    ],
    "DAMEfinder": [
        "VariantAnnotation"
    ],
    "DaMiRseq": [],
    "decompTumor2Sig": [
        "VariantAnnotation"
    ],
    "deconvR": [
        "minfi"
    ],
    "deepSNV": [
        "VariantAnnotation"
    ],
    "DeMixT": [
        "DSS"
    ],
    "derfinder": [
        "GenomicFiles",
        "VariantAnnotation"
    ],
    "derfinderPlot": [
        "GenomicFiles",
        "VariantAnnotation",
        "biovizBase",
        "derfinder",
        "ggbio"
    ],
    "DEScan2": [
        "ChIPpeakAnno",
        "regioneR"
    ],
    "DESpace": [
        "SpatialExperiment"
    ],
    "DiffBind": [
        "GreyListChIP"
    ],
    "diffHic": [],
    "diffUTR": [],
    "Dino": [
        "scran"
    ],
    "distinct": [
        "scater"
    ],
    "DMCFB": [],
    "DMRcate": [
        "DSS",
        "Gviz",
        "VariantAnnotation",
        "biovizBase",
        "methylumi",
        "minfi",
        "missMethyl"
    ],
    "DMRforPairs": [
        "Gviz",
        "VariantAnnotation",
        "biovizBase"
    ],
    "dmrseq": [
        "annotatr",
        "regioneR"
    ],
    "DominoEffect": [
        "VariantAnnotation"
    ],
    "dpeak": [],
    "drugTargetInteractions": [],
    "DSS": [],
    "EasyCellType": [],
    "eegc": [],
    "enhancerHomologSearch": [
        "TFBSTools",
        "motifmatchr"
    ],
    "ENmix": [
        "minfi"
    ],
    "enrichTF": [
        "TFBSTools",
        "motifmatchr",
        "pipeFrame"
    ],
    "ensemblVEP": [
        "VariantAnnotation"
    ],
    "epialleleR": [
        "VariantAnnotation"
    ],
    "EpiCompare": [
        "genomation"
    ],
    "epigraHMM": [
        "GreyListChIP"
    ],
    "epimutacions": [
        "Gviz",
        "VariantAnnotation",
        "biovizBase",
        "minfi"
    ],
    "epivizr": [
        "epivizrData"
    ],
    "epivizrChart": [
        "epivizrData"
    ],
    "epivizrData": [],
    "epivizrStandalone": [
        "epivizr",
        "epivizrData"
    ],
    "erma": [
        "GenomicFiles",
        "VariantAnnotation"
    ],
    "esATAC": [
        "TFBSTools",
        "motifmatchr",
        "pipeFrame"
    ],
    "escheR": [
        "SpatialExperiment",
        "scater"
    ],
    "EventPointer": [],
    "exomePeak2": [],
    "ExperimentHubData": [
        "AnnotationHubData"
    ],
    "ExperimentSubset": [
        "SpatialExperiment"
    ],
    "extraChIPs": [
        "GenomicInteractions",
        "Gviz",
        "VariantAnnotation",
        "biovizBase"
    ],
    "fCCAC": [
        "genomation"
    ],
    "fcoex": [],
    "fcScan": [
        "VariantAnnotation"
    ],
    "FEAST": [
        "TSCAN"
    ],
    "ffpe": [
        "lumi",
        "methylumi",
        "minfi"
    ],
    "FLAMES": [
        "VariantAnnotation",
        "biovizBase",
        "ggbio",
        "scater",
        "scran"
    ],
    "FRASER": [],
    "funtooNorm": [
        "minfi"
    ],
    "GA4GHclient": [
        "VariantAnnotation"
    ],
    "GA4GHshiny": [
        "GA4GHclient",
        "VariantAnnotation"
    ],
    "GARS": [
        "DaMiRseq"
    ],
    "gcapc": [],
    "GDCRNATools": [],
    "genbankr": [
        "VariantAnnotation"
    ],
    "GeneStructureTools": [
        "Gviz",
        "VariantAnnotation",
        "biovizBase"
    ],
    "genomation": [],
    "GenomicFiles": [
        "VariantAnnotation"
    ],
    "GenomicInteractions": [
        "Gviz",
        "VariantAnnotation",
        "biovizBase"
    ],
    "GenomicOZone": [
        "VariantAnnotation",
        "biovizBase",
        "ggbio"
    ],
    "GenVisR": [
        "VariantAnnotation"
    ],
    "gespeR": [
        "cellHTS2"
    ],
    "ggbio": [
        "VariantAnnotation",
        "biovizBase"
    ],
    "ggspavis": [
        "SpatialExperiment"
    ],
    "gmapR": [
        "VariantAnnotation"
    ],
    "GOTHiC": [],
    "GreyListChIP": [],
    "GSReg": [],
    "GUIDEseq": [
        "CRISPRseek",
        "ChIPpeakAnno",
        "regioneR"
    ],
    "Gviz": [
        "VariantAnnotation",
        "biovizBase"
    ],
    "gwascat": [
        "VariantAnnotation"
    ],
    "gwasurvivr": [
        "VariantAnnotation"
    ],
    "HelloRanges": [
        "VariantAnnotation"
    ],
    "hiAnnotator": [],
    "HiCDCPlus": [
        "GenomicInteractions",
        "Gviz",
        "VariantAnnotation",
        "biovizBase"
    ],
    "HiLDA": [],
    "hiReadsProcessor": [
        "hiAnnotator"
    ],
    "HTSeqGenie": [
        "VariantAnnotation",
        "VariantTools",
        "gmapR"
    ],
    "icetea": [
        "VariantAnnotation"
    ],
    "iCheck": [
        "lumi",
        "methylumi",
        "minfi"
    ],
    "iCNV": [
        "CODEX"
    ],
    "ideal": [],
    "igvR": [
        "VariantAnnotation"
    ],
    "IMAS": [],
    "imcRtools": [
        "SpatialExperiment",
        "cytomapper"
    ],
    "InPAS": [
        "cleanUpdTSeq"
    ],
    "intansv": [
        "VariantAnnotation",
        "biovizBase",
        "ggbio"
    ],
    "interactiveDisplay": [],
    "IntEREst": [
        "GenomicFiles",
        "VariantAnnotation"
    ],
    "IRISFGM": [
        "scater",
        "scran"
    ],
    "IsoformSwitchAnalyzeR": [
        "tximeta"
    ],
    "karyoploteR": [
        "VariantAnnotation",
        "biovizBase",
        "regioneR"
    ],
    "katdetectr": [
        "VariantAnnotation"
    ],
    "kissDE": [
        "DSS"
    ],
    "lineagespot": [
        "VariantAnnotation"
    ],
    "lisaClust": [
        "SpatialExperiment",
        "spicyR"
    ],
    "lumi": [
        "methylumi",
        "minfi"
    ],
    "m6Aboost": [],
    "MADSEQ": [
        "VariantAnnotation"
    ],
    "MAGAR": [
        "RnBeads",
        "methylumi",
        "minfi"
    ],
    "magpie": [],
    "MAIT": [],
    "mariner": [],
    "maser": [
        "Gviz",
        "VariantAnnotation",
        "biovizBase"
    ],
    "MatrixRider": [
        "TFBSTools"
    ],
    "mCSEA": [
        "Gviz",
        "VariantAnnotation",
        "biovizBase"
    ],
    "MEAL": [
        "Gviz",
        "VariantAnnotation",
        "biovizBase",
        "methylumi",
        "minfi",
        "missMethyl"
    ],
    "MEAT": [
        "lumi",
        "methylumi",
        "minfi",
        "wateRmelon"
    ],
    "MEB": [
        "scater"
    ],
    "MEDIPS": [],
    "meshr": [],
    "MetaboSignal": [],
    "metagene": [],
    "MetaPhOR": [],
    "MethReg": [],
    "methrix": [],
    "MethylAid": [
        "minfi"
    ],
    "methylCC": [
        "minfi"
    ],
    "methylclock": [
        "AnnotationHubData",
        "ExperimentHubData",
        "minfi"
    ],
    "methylGSA": [
        "methylumi",
        "minfi",
        "missMethyl"
    ],
    "methylPipe": [
        "Gviz",
        "VariantAnnotation",
        "biovizBase"
    ],
    "MethylSeekR": [],
    "methylSig": [
        "DSS"
    ],
    "methylumi": [
        "minfi"
    ],
    "mia": [
        "scater"
    ],
    "miaViz": [
        "mia",
        "scater"
    ],
    "microbiomeMarker": [
        "ANCOMBC",
        "mia",
        "scater"
    ],
    "MicrobiomeProfiler": [],
    "MineICA": [
        "lumi",
        "methylumi",
        "minfi"
    ],
    "minfi": [],
    "MinimumDistance": [
        "VanillaICE"
    ],
    "MIRA": [],
    "miRSM": [],
    "missMethyl": [
        "methylumi",
        "minfi"
    ],
    "mitoClone2": [
        "VariantAnnotation",
        "deepSNV"
    ],
    "MMAPPR2": [
        "VariantAnnotation",
        "VariantTools",
        "ensemblVEP",
        "gmapR"
    ],
    "MMDiff2": [],
    "MoleculeExperiment": [
        "SpatialExperiment"
    ],
    "monaLisa": [
        "TFBSTools"
    ],
    "Motif2Site": [],
    "motifbreakR": [
        "Gviz",
        "TFBSTools",
        "VariantAnnotation",
        "biovizBase",
        "motifStack"
    ],
    "motifmatchr": [
        "TFBSTools"
    ],
    "motifStack": [
        "TFBSTools"
    ],
    "msgbsR": [
        "VariantAnnotation",
        "biovizBase",
        "ggbio"
    ],
    "msImpute": [
        "scran"
    ],
    "msqrob2": [],
    "multicrispr": [
        "CRISPRseek",
        "VariantAnnotation",
        "biovizBase",
        "karyoploteR",
        "regioneR"
    ],
    "mumosa": [
        "scran"
    ],
    "MungeSumstats": [
        "VariantAnnotation"
    ],
    "muscat": [
        "scater"
    ],
    "musicatk": [
        "VariantAnnotation",
        "decompTumor2Sig"
    ],
    "MutationalPatterns": [
        "VariantAnnotation"
    ],
    "myvariant": [
        "VariantAnnotation"
    ],
    "NADfinder": [
        "ATACseqQC",
        "ChIPpeakAnno",
        "Gviz",
        "TFBSTools",
        "VariantAnnotation",
        "biovizBase",
        "motifStack",
        "regioneR",
        "trackViewer"
    ],
    "NanoMethViz": [],
    "netSmooth": [
        "clusterExperiment",
        "scater",
        "zinbwave"
    ],
    "netZooR": [
        "minfi",
        "quantro",
        "yarn"
    ],
    "nnSVG": [
        "SpatialExperiment"
    ],
    "NoRCE": [],
    "NxtIRFcore": [],
    "octad": [
        "RUVSeq"
    ],
    "ODER": [
        "GenomicFiles",
        "VariantAnnotation",
        "derfinder"
    ],
    "OGRE": [
        "Gviz",
        "VariantAnnotation",
        "biovizBase"
    ],
    "omada": [],
    "OmicsLonDA": [],
    "OMICsPCA": [
        "HelloRanges",
        "VariantAnnotation"
    ],
    "ORFhunteR": [],
    "ORFik": [],
    "OutSplice": [
        "Repitools"
    ],
    "pageRank": [
        "TFBSTools",
        "motifmatchr"
    ],
    "PanomiR": [],
    "peco": [
        "scater"
    ],
    "periodicDNA": [],
    "phenoTest": [],
    "PhyloProfile": [],
    "PING": [
        "Gviz",
        "VariantAnnotation",
        "biovizBase"
    ],
    "pipeComp": [
        "scater",
        "scran"
    ],
    "pipeFrame": [],
    "podkat": [],
    "pogos": [],
    "POWSC": [],
    "preciseTAD": [],
    "primirTSS": [
        "Gviz",
        "TFBSTools",
        "VariantAnnotation",
        "biovizBase"
    ],
    "PrInCE": [],
    "profileplyr": [
        "rGREAT"
    ],
    "projectR": [],
    "pRoloc": [],
    "pRolocGUI": [
        "pRoloc"
    ],
    "proteasy": [],
    "ProteoDisco": [
        "VariantAnnotation"
    ],
    "protGear": [],
    "psichomics": [
        "GenomicFiles",
        "VariantAnnotation",
        "derfinder",
        "recount"
    ],
    "psygenet2r": [],
    "puma": [],
    "PureCN": [
        "VariantAnnotation"
    ],
    "Pviz": [
        "Gviz",
        "VariantAnnotation",
        "biovizBase"
    ],
    "qsea": [],
    "quantro": [
        "minfi"
    ],
    "QuasR": [
        "GenomicFiles",
        "VariantAnnotation"
    ],
    "R3CPET": [
        "VariantAnnotation",
        "biovizBase",
        "ggbio"
    ],
    "R453Plus1Toolbox": [
        "VariantAnnotation"
    ],
    "RareVariantVis": [
        "VariantAnnotation"
    ],
    "Rbec": [],
    "RCAS": [
        "genomation"
    ],
    "recount": [
        "GenomicFiles",
        "VariantAnnotation",
        "derfinder"
    ],
    "recountmethylation": [
        "minfi"
    ],
    "REDseq": [
        "ChIPpeakAnno",
        "regioneR"
    ],
    "regioneR": [],
    "regioneReloaded": [
        "regioneR"
    ],
    "regionReport": [
        "GenomicFiles",
        "VariantAnnotation",
        "derfinder"
    ],
    "regutools": [
        "Gviz",
        "VariantAnnotation",
        "biovizBase"
    ],
    "REMP": [
        "minfi"
    ],
    "Repitools": [],
    "ReportingTools": [
        "VariantAnnotation",
        "biovizBase",
        "ggbio"
    ],
    "RESOLVE": [
        "MutationalPatterns",
        "VariantAnnotation"
    ],
    "rGADEM": [],
    "RgnTX": [
        "regioneR"
    ],
    "rGREAT": [],
    "rgsepd": [],
    "Rhisat2": [],
    "RiboCrypt": [
        "ORFik"
    ],
    "RiboProfiling": [
        "VariantAnnotation",
        "biovizBase",
        "ggbio"
    ],
    "ribosomeProfilingQC": [
        "RUVSeq",
        "TFBSTools",
        "motifStack"
    ],
    "RIPAT": [
        "VariantAnnotation",
        "biovizBase",
        "karyoploteR",
        "regioneR"
    ],
    "RITAN": [],
    "RLSeq": [
        "regioneR"
    ],
    "Rmmquant": [],
    "RNAAgeCalc": [
        "GenomicFiles",
        "VariantAnnotation",
        "derfinder",
        "recount"
    ],
    "rnaEditr": [],
    "RNAinteract": [
        "cellHTS2"
    ],
    "RNAmodR": [
        "Gviz",
        "VariantAnnotation",
        "biovizBase"
    ],
    "RNAmodR.AlkAnilineSeq": [
        "Gviz",
        "RNAmodR",
        "VariantAnnotation",
        "biovizBase"
    ],
    "RNAmodR.ML": [
        "Gviz",
        "RNAmodR",
        "VariantAnnotation",
        "biovizBase"
    ],
    "RNAmodR.RiboMethSeq": [
        "Gviz",
        "RNAmodR",
        "VariantAnnotation",
        "biovizBase"
    ],
    "RnaSeqSampleSize": [
        "GenomicFiles",
        "VariantAnnotation",
        "derfinder",
        "recount"
    ],
    "RnBeads": [
        "methylumi",
        "minfi"
    ],
    "Rqc": [
        "GenomicFiles",
        "VariantAnnotation",
        "biovizBase"
    ],
    "RTCGAToolbox": [],
    "RTNsurvival": [],
    "rTRMui": [],
    "RUVSeq": [],
    "scanMiRApp": [],
    "SCANVIS": [],
    "SCArray.sat": [],
    "scater": [],
    "scBFA": [
        "zinbwave"
    ],
    "scCB2": [],
    "scClassify": [],
    "scDblFinder": [
        "scater",
        "scran"
    ],
    "scDD": [
        "scran"
    ],
    "scFeatures": [
        "SingleCellSignalR",
        "SpatialExperiment",
        "scran"
    ],
    "scMerge": [
        "scater",
        "scran"
    ],
    "scmeth": [
        "annotatr",
        "regioneR"
    ],
    "scone": [
        "RUVSeq"
    ],
    "SCOPE": [],
    "scoreInvHap": [
        "VariantAnnotation"
    ],
    "scran": [],
    "scRNAseqApp": [
        "slingshot"
    ],
    "scruff": [
        "VariantAnnotation",
        "biovizBase",
        "ggbio"
    ],
    "scTensor": [
        "meshr"
    ],
    "scTGIF": [],
    "scTreeViz": [
        "epivizr",
        "epivizrData",
        "scater",
        "scran"
    ],
    "scviR": [
        "scater"
    ],
    "segmenter": [],
    "selectKSigs": [
        "HiLDA"
    ],
    "seqArchRplus": [],
    "seqCAT": [
        "VariantAnnotation"
    ],
    "shinyepico": [
        "minfi"
    ],
    "shinyMethyl": [
        "minfi"
    ],
    "signeR": [
        "VariantAnnotation"
    ],
    "signifinder": [],
    "SigsPack": [
        "VariantAnnotation"
    ],
    "simpleSeg": [
        "SpatialExperiment",
        "cytomapper"
    ],
    "SingleCellSignalR": [
        "scran"
    ],
    "singleCellTK": [
        "TSCAN",
        "celda",
        "scDblFinder",
        "scMerge",
        "scater",
        "scran",
        "zinbwave"
    ],
    "SingleMoleculeFootprinting": [
        "GenomicFiles",
        "QuasR",
        "VariantAnnotation"
    ],
    "SISPA": [],
    "sitadela": [],
    "skewr": [
        "lumi",
        "methylumi",
        "minfi",
        "wateRmelon"
    ],
    "slingshot": [],
    "SMITE": [],
    "snapCGH": [
        "tilingArray"
    ],
    "SNPhood": [
        "VariantAnnotation"
    ],
    "SomaticSignatures": [
        "VariantAnnotation",
        "biovizBase",
        "ggbio"
    ],
    "Spaniel": [
        "scater",
        "scran"
    ],
    "SparseSignatures": [],
    "spaSim": [
        "SpatialExperiment"
    ],
    "spatialDE": [
        "SpatialExperiment"
    ],
    "SpatialExperiment": [],
    "SpatialFeatureExperiment": [
        "SpatialExperiment"
    ],
    "spatialHeatmap": [
        "scater",
        "scran"
    ],
    "spatzie": [
        "GenomicInteractions",
        "Gviz",
        "TFBSTools",
        "VariantAnnotation",
        "biovizBase",
        "motifmatchr"
    ],
    "SPIAT": [
        "SpatialExperiment"
    ],
    "spicyR": [
        "SpatialExperiment"
    ],
    "spiky": [],
    "splatter": [],
    "SpliceWiz": [],
    "SPLINTER": [
        "Gviz",
        "VariantAnnotation",
        "biovizBase"
    ],
    "SpotClean": [
        "SpatialExperiment"
    ],
    "standR": [
        "RUVSeq",
        "SpatialExperiment"
    ],
    "staRank": [
        "cellHTS2"
    ],
    "StarBioTrek": [],
    "stJoincount": [
        "SpatialExperiment"
    ],
    "StructuralVariantAnnotation": [
        "VariantAnnotation"
    ],
    "svaNUMT": [
        "StructuralVariantAnnotation",
        "VariantAnnotation"
    ],
    "svaRetro": [
        "StructuralVariantAnnotation",
        "VariantAnnotation"
    ],
    "TAPseq": [],
    "TBSignatureProfiler": [],
    "TDbasedUFEadv": [],
    "terraTCGAdata": [],
    "TFBSTools": [],
    "TFEA.ChIP": [],
    "TFHAZ": [
        "ORFik"
    ],
    "tilingArray": [],
    "TimiRGeN": [],
    "TitanCNA": [
        "VariantAnnotation"
    ],
    "tLOH": [
        "VariantAnnotation"
    ],
    "TNBC.CMS": [],
    "TOP": [],
    "trackViewer": [
        "Gviz",
        "VariantAnnotation",
        "biovizBase"
    ],
    "tradeSeq": [
        "slingshot"
    ],
    "traseR": [],
    "traviz": [
        "slingshot"
    ],
    "trena": [],
    "tricycle": [
        "scater"
    ],
    "tRNAscanImport": [],
    "TSCAN": [],
    "tscR": [],
    "TVTB": [
        "Gviz",
        "VariantAnnotation",
        "biovizBase",
        "ensemblVEP"
    ],
    "txcutr": [],
    "tximeta": [],
    "Ularcirc": [],
    "UMI4Cats": [
        "regioneR"
    ],
    "uncoverappLib": [
        "Gviz",
        "VariantAnnotation",
        "biovizBase"
    ],
    "Uniquorn": [
        "VariantAnnotation"
    ],
    "VAExprs": [
        "scater"
    ],
    "VanillaICE": [],
    "VarCon": [],
    "VariantAnnotation": [],
    "VariantFiltering": [
        "Gviz",
        "VariantAnnotation",
        "biovizBase"
    ],
    "VariantTools": [
        "VariantAnnotation"
    ],
    "VCFArray": [
        "GenomicFiles",
        "VariantAnnotation"
    ],
    "Voyager": [
        "SpatialExperiment",
        "SpatialFeatureExperiment"
    ],
    "vtpnet": [
        "VariantAnnotation",
        "gwascat"
    ],
    "vulcan": [
        "ChIPpeakAnno",
        "DiffBind",
        "GreyListChIP",
        "regioneR"
    ],
    "wateRmelon": [
        "lumi",
        "methylumi",
        "minfi"
    ],
    "XDE": [],
    "Xeva": [],
    "XNAString": [],
    "YAPSA": [
        "SomaticSignatures",
        "VariantAnnotation",
        "biovizBase",
        "ggbio"
    ],
    "yarn": [
        "minfi",
        "quantro"
    ],
    "zenith": [],
    "zinbwave": [],
    "ZygosityPredictor": [
        "VariantAnnotation"
    ]
}