{
    "ADaCGH2": [
        "snapCGH",
        "tilingArray"
    ],
    "affycoretools": [
        "ReportingTools",
        "ggbio"
    ],
    "AgiMicroRna": [
        "ReportingTools",
        "affycoretools",
        "ggbio"
    ],
    "airpart": [
        "scater"
    ],
    "alabaster": [
        "SpatialExperiment",
        "alabaster.spatial"
    ],
    "alabaster.spatial": [
        "SpatialExperiment"
    ],
    "AllelicImbalance": [
        "Gviz"
    ],
    "alpine": [],
    "amplican": [],
    "ANCOMBC": [
        "mia",
        "scater"
    ],
    "appreci8R": [],
    "arrayMvout": [
        "lumi"
    ],
    "ASpli": [
        "Gviz"
    ],
    "ATACCoGAPS": [
        "motifmatchr",
        "projectR"
    ],
    "ATACseqQC": [
        "motifStack"
    ],
    "ATACseqTFEA": [
        "motifmatchr"
    ],
    "atSNP": [
        "motifStack"
    ],
    "bandle": [
        "pRoloc"
    ],
    "BASiCS": [
        "scran"
    ],
    "BASiCStan": [
        "BASiCS",
        "scran"
    ],
    "BayesSpace": [
        "scater",
        "scran"
    ],
    "benchdamic": [
        "ANCOMBC",
        "mia",
        "scater",
        "zinbwave"
    ],
    "BGmix": [],
    "bigmelon": [
        "lumi",
        "wateRmelon"
    ],
    "BindingSiteFinder": [
        "Gviz"
    ],
    "BioTIP": [
        "scran"
    ],
    "biscuiteer": [],
    "BiSeq": [],
    "BOBaFIT": [
        "ggbio"
    ],
    "brainflowprobes": [
        "GenomicFiles",
        "derfinder",
        "derfinderPlot",
        "ggbio"
    ],
    "BubbleTree": [],
    "CAFE": [
        "ggbio"
    ],
    "CAGEfightR": [
        "GenomicFiles",
        "GenomicInteractions",
        "Gviz"
    ],
    "cageminer": [
        "ggbio"
    ],
    "CAGEr": [
        "CAGEfightR",
        "GenomicFiles",
        "GenomicInteractions",
        "Gviz"
    ],
    "canceR": [
        "phenoTest"
    ],
    "CATALYST": [
        "scater"
    ],
    "cbaf": [
        "cBioPortalData"
    ],
    "cBioPortalData": [],
    "CCPROMISE": [],
    "celda": [
        "scater",
        "scran"
    ],
    "cellHTS2": [],
    "CelliD": [
        "scater"
    ],
    "CellMixS": [
        "scater"
    ],
    "CEMiTool": [],
    "CeTF": [],
    "ChAMP": [
        "DMRcate",
        "Gviz",
        "lumi",
        "missMethyl",
        "wateRmelon"
    ],
    "ChIC": [],
    "chimeraviz": [
        "Gviz"
    ],
    "ChIPComp": [],
    "ChIPexoQual": [],
    "ChIPQC": [],
    "ChromSCape": [
        "scater",
        "scran"
    ],
    "cicero": [
        "Gviz"
    ],
    "circRNAprofiler": [
        "gwascat"
    ],
    "CircSeqAlignTk": [],
    "CiteFuse": [
        "scran"
    ],
    "clusterExperiment": [
        "zinbwave"
    ],
    "CNVfilteR": [
        "CopyNumberPlots",
        "karyoploteR"
    ],
    "CNViz": [
        "CopyNumberPlots",
        "karyoploteR"
    ],
    "comapr": [
        "Gviz"
    ],
    "coMET": [
        "Gviz"
    ],
    "compEpiTools": [
        "Gviz",
        "methylPipe"
    ],
    "condiments": [
        "distinct",
        "scater",
        "slingshot"
    ],
    "consensusDE": [],
    "contiBAIT": [
        "GenomicFiles"
    ],
    "CopyNumberPlots": [
        "karyoploteR"
    ],
    "CRISPRseek": [],
    "crisprseekplus": [
        "CRISPRseek",
        "GUIDEseq"
    ],
    "crisprVerse": [
        "Gviz",
        "crisprViz"
    ],
    "crisprViz": [
        "Gviz"
    ],
    "CTSV": [
        "SpatialExperiment"
    ],
    "cummeRbund": [
        "Gviz"
    ],
    "cytofQC": [
        "CATALYST",
        "scater"
    ],
    "cytomapper": [
        "SpatialExperiment"
    ],
    "cytoviewer": [
        "SpatialExperiment",
        "cytomapper"
    ],
    "dagLogo": [
        "motifStack"
    ],
    "decompTumor2Sig": [],
    "DeMixT": [],
    "derfinder": [
        "GenomicFiles"
    ],
    "derfinderPlot": [
        "GenomicFiles",
        "derfinder",
        "ggbio"
    ],
    "DESpace": [
        "SpatialExperiment"
    ],
    "Dino": [
        "scran"
    ],
    "distinct": [
        "scater"
    ],
    "DMCFB": [],
    "DMRcate": [
        "Gviz",
        "missMethyl"
    ],
    "DMRforPairs": [
        "Gviz"
    ],
    "DominoEffect": [],
    "EasyCellType": [],
    "eegc": [],
    "enhancerHomologSearch": [
        "motifmatchr"
    ],
    "enrichTF": [
        "motifmatchr"
    ],
    "ensemblVEP": [],
    "epimutacions": [
        "Gviz"
    ],
    "epivizr": [],
    "epivizrChart": [],
    "epivizrStandalone": [
        "epivizr"
    ],
    "erma": [
        "GenomicFiles"
    ],
    "esATAC": [
        "motifmatchr"
    ],
    "escheR": [
        "SpatialExperiment",
        "scater"
    ],
    "EventPointer": [],
    "exomePeak2": [],
    "ExperimentHubData": [],
    "ExperimentSubset": [
        "SpatialExperiment"
    ],
    "extraChIPs": [
        "GenomicInteractions",
        "Gviz"
    ],
    "fcoex": [],
    "fcScan": [],
    "FEAST": [
        "TSCAN"
    ],
    "ffpe": [
        "lumi"
    ],
    "FLAMES": [
        "ggbio",
        "scater",
        "scran"
    ],
    "GA4GHclient": [],
    "GA4GHshiny": [
        "GA4GHclient"
    ],
    "GDCRNATools": [],
    "genbankr": [],
    "GeneStructureTools": [
        "Gviz"
    ],
    "GenomicFiles": [],
    "GenomicInteractions": [
        "Gviz"
    ],
    "GenomicOZone": [
        "ggbio"
    ],
    "GenVisR": [],
    "gespeR": [
        "cellHTS2"
    ],
    "ggbio": [],
    "ggspavis": [
        "SpatialExperiment"
    ],
    "gmapR": [],
    "GUIDEseq": [
        "CRISPRseek"
    ],
    "Gviz": [],
    "gwascat": [],
    "gwasurvivr": [],
    "HelloRanges": [],
    "HiCDCPlus": [
        "GenomicInteractions",
        "Gviz"
    ],
    "HTSeqGenie": [
        "VariantTools",
        "gmapR"
    ],
    "icetea": [],
    "iCheck": [
        "lumi"
    ],
    "igvR": [],
    "imcRtools": [
        "SpatialExperiment",
        "cytomapper"
    ],
    "InPAS": [],
    "intansv": [
        "ggbio"
    ],
    "interactiveDisplay": [],
    "IntEREst": [
        "GenomicFiles"
    ],
    "IRISFGM": [
        "scater",
        "scran"
    ],
    "IsoformSwitchAnalyzeR": [],
    "karyoploteR": [],
    "katdetectr": [],
    "kissDE": [],
    "lineagespot": [],
    "lisaClust": [
        "SpatialExperiment",
        "spicyR"
    ],
    "lumi": [],
    "MADSEQ": [],
    "MAGAR": [
        "RnBeads"
    ],
    "MAIT": [],
    "maser": [
        "Gviz"
    ],
    "MatrixRider": [],
    "mCSEA": [
        "Gviz"
    ],
    "MEAL": [
        "Gviz",
        "missMethyl"
    ],
    "MEAT": [
        "lumi",
        "wateRmelon"
    ],
    "MEB": [
        "scater"
    ],
    "meshr": [],
    "MetaPhOR": [],
    "MethReg": [],
    "methylclock": [
        "ExperimentHubData"
    ],
    "methylGSA": [
        "missMethyl"
    ],
    "methylPipe": [
        "Gviz"
    ],
    "methylSig": [],
    "mia": [
        "scater"
    ],
    "miaViz": [
        "mia",
        "scater"
    ],
    "microbiomeMarker": [
        "ANCOMBC",
        "mia",
        "scater"
    ],
    "MicrobiomeProfiler": [],
    "MineICA": [
        "lumi"
    ],
    "MinimumDistance": [],
    "missMethyl": [],
    "mitoClone2": [],
    "MMAPPR2": [
        "VariantTools",
        "ensemblVEP",
        "gmapR"
    ],
    "MoleculeExperiment": [
        "SpatialExperiment"
    ],
    "monaLisa": [],
    "motifbreakR": [
        "Gviz",
        "motifStack"
    ],
    "motifmatchr": [],
    "motifStack": [],
    "msgbsR": [
        "ggbio"
    ],
    "msImpute": [
        "scran"
    ],
    "msqrob2": [],
    "multicrispr": [
        "CRISPRseek",
        "karyoploteR"
    ],
    "mumosa": [
        "scran"
    ],
    "MungeSumstats": [],
    "muscat": [
        "scater"
    ],
    "musicatk": [
        "decompTumor2Sig"
    ],
    "MutationalPatterns": [],
    "myvariant": [],
    "NADfinder": [
        "ATACseqQC",
        "Gviz",
        "motifStack",
        "trackViewer"
    ],
    "netSmooth": [
        "clusterExperiment",
        "scater",
        "zinbwave"
    ],
    "netZooR": [
        "yarn"
    ],
    "nnSVG": [
        "SpatialExperiment"
    ],
    "octad": [],
    "ODER": [
        "GenomicFiles",
        "derfinder"
    ],
    "OGRE": [
        "Gviz"
    ],
    "omada": [],
    "OmicsLonDA": [],
    "OMICsPCA": [
        "HelloRanges"
    ],
    "pageRank": [
        "motifmatchr"
    ],
    "PanomiR": [],
    "peco": [
        "scater"
    ],
    "phenoTest": [],
    "PhyloProfile": [],
    "PING": [
        "Gviz"
    ],
    "pipeComp": [
        "scater",
        "scran"
    ],
    "pogos": [],
    "POWSC": [],
    "primirTSS": [
        "Gviz"
    ],
    "PrInCE": [],
    "projectR": [],
    "pRoloc": [],
    "pRolocGUI": [
        "pRoloc"
    ],
    "ProteoDisco": [],
    "protGear": [],
    "psichomics": [
        "GenomicFiles",
        "derfinder",
        "recount"
    ],
    "psygenet2r": [],
    "puma": [],
    "PureCN": [],
    "Pviz": [
        "Gviz"
    ],
    "QuasR": [
        "GenomicFiles"
    ],
    "R3CPET": [
        "ggbio"
    ],
    "R453Plus1Toolbox": [],
    "RareVariantVis": [],
    "Rbec": [],
    "recount": [
        "GenomicFiles",
        "derfinder"
    ],
    "REDseq": [],
    "regionReport": [
        "GenomicFiles",
        "derfinder"
    ],
    "regutools": [
        "Gviz"
    ],
    "ReportingTools": [
        "ggbio"
    ],
    "RESOLVE": [
        "MutationalPatterns"
    ],
    "RiboProfiling": [
        "ggbio"
    ],
    "ribosomeProfilingQC": [
        "motifStack"
    ],
    "RIPAT": [
        "karyoploteR"
    ],
    "RNAAgeCalc": [
        "GenomicFiles",
        "derfinder",
        "recount"
    ],
    "RNAinteract": [
        "cellHTS2"
    ],
    "RNAmodR": [
        "Gviz"
    ],
    "RNAmodR.AlkAnilineSeq": [
        "Gviz",
        "RNAmodR"
    ],
    "RNAmodR.ML": [
        "Gviz",
        "RNAmodR"
    ],
    "RNAmodR.RiboMethSeq": [
        "Gviz",
        "RNAmodR"
    ],
    "RnaSeqSampleSize": [
        "GenomicFiles",
        "derfinder",
        "recount"
    ],
    "RnBeads": [],
    "Rqc": [
        "GenomicFiles"
    ],
    "RTNsurvival": [],
    "SCANVIS": [],
    "SCArray.sat": [],
    "scater": [],
    "scBFA": [
        "zinbwave"
    ],
    "scCB2": [],
    "scClassify": [],
    "scDblFinder": [
        "scater",
        "scran"
    ],
    "scDD": [
        "scran"
    ],
    "scFeatures": [
        "SingleCellSignalR",
        "SpatialExperiment",
        "scran"
    ],
    "scMerge": [
        "scater",
        "scran"
    ],
    "scmeth": [],
    "scone": [],
    "scoreInvHap": [],
    "scran": [],
    "scRNAseqApp": [
        "slingshot"
    ],
    "scruff": [
        "ggbio"
    ],
    "scTensor": [
        "meshr"
    ],
    "scTGIF": [],
    "scTreeViz": [
        "epivizr",
        "scater",
        "scran"
    ],
    "scviR": [
        "scater"
    ],
    "seqCAT": [],
    "signeR": [],
    "SigsPack": [],
    "simpleSeg": [
        "SpatialExperiment",
        "cytomapper"
    ],
    "SingleCellSignalR": [
        "scran"
    ],
    "singleCellTK": [
        "TSCAN",
        "celda",
        "scDblFinder",
        "scMerge",
        "scater",
        "scran",
        "zinbwave"
    ],
    "SingleMoleculeFootprinting": [
        "GenomicFiles",
        "QuasR"
    ],
    "SISPA": [],
    "skewr": [
        "lumi",
        "wateRmelon"
    ],
    "slingshot": [],
    "snapCGH": [
        "tilingArray"
    ],
    "SNPhood": [],
    "SomaticSignatures": [
        "ggbio"
    ],
    "Spaniel": [
        "scater",
        "scran"
    ],
    "spaSim": [
        "SpatialExperiment"
    ],
    "spatialDE": [
        "SpatialExperiment"
    ],
    "SpatialExperiment": [],
    "SpatialFeatureExperiment": [
        "SpatialExperiment"
    ],
    "spatialHeatmap": [
        "scater",
        "scran"
    ],
    "spatzie": [
        "GenomicInteractions",
        "Gviz",
        "motifmatchr"
    ],
    "SPIAT": [
        "SpatialExperiment"
    ],
    "spicyR": [
        "SpatialExperiment"
    ],
    "splatter": [],
    "SPLINTER": [
        "Gviz"
    ],
    "SpotClean": [
        "SpatialExperiment"
    ],
    "standR": [
        "SpatialExperiment"
    ],
    "staRank": [
        "cellHTS2"
    ],
    "StarBioTrek": [],
    "stJoincount": [
        "SpatialExperiment"
    ],
    "StructuralVariantAnnotation": [],
    "svaNUMT": [
        "StructuralVariantAnnotation"
    ],
    "svaRetro": [
        "StructuralVariantAnnotation"
    ],
    "TDbasedUFEadv": [],
    "tilingArray": [],
    "TimiRGeN": [],
    "TitanCNA": [],
    "tLOH": [],
    "TNBC.CMS": [],
    "TOP": [],
    "trackViewer": [
        "Gviz"
    ],
    "tradeSeq": [
        "slingshot"
    ],
    "traviz": [
        "slingshot"
    ],
    "tricycle": [
        "scater"
    ],
    "TSCAN": [],
    "tscR": [],
    "TVTB": [
        "Gviz",
        "ensemblVEP"
    ],
    "uncoverappLib": [
        "Gviz"
    ],
    "Uniquorn": [],
    "VAExprs": [
        "scater"
    ],
    "VariantFiltering": [
        "Gviz"
    ],
    "VariantTools": [],
    "VCFArray": [
        "GenomicFiles"
    ],
    "Voyager": [
        "SpatialExperiment",
        "SpatialFeatureExperiment"
    ],
    "vtpnet": [
        "gwascat"
    ],
    "vulcan": [],
    "wateRmelon": [
        "lumi"
    ],
    "XDE": [],
    "Xeva": [],
    "YAPSA": [
        "SomaticSignatures",
        "ggbio"
    ],
    "yarn": [],
    "zenith": [],
    "zinbwave": [],
    "ZygosityPredictor": []
}